keneth/di_contracts/__init__.py
keneth/di_contracts/container.py
keneth/di_contracts/container_context.py
keneth/di_contracts/container_context_target.py
keneth/di_contracts/service.py
keneth_di_contracts-0.1.1.dist-info/licenses/LICENSE
keneth_di_contracts-0.1.1.dist-info/METADATA
keneth_di_contracts-0.1.1.dist-info/WHEEL
keneth_di_contracts-0.1.1.dist-info/top_level.txt
keneth_di_contracts-0.1.1.dist-info/RECORD
