Metadata-Version: 2.4
Name: keneth-di-contracts
Version: 0.1.1
Summary: Dependency Injector Contracts for the Keneth Python web framework.
Author-email: Ismaël Lucas de Leyssac <geodgit@duck.com>
License:                                  Apache License
Project-URL: Homepage, https://github.com/keneth-framework/di-contracts
Requires-Python: >=3.12
License-File: LICENSE
Dynamic: license-file
